{"data":[{"testName":"ProfileList_Create-9","executionTime":346},{"0":{"DiskDataSet":{"AvgDiskQueueLength":0.002940589,"ReadBytesPerSecond":0.0,"WriteBytesPerSecond":1293654.25,"AvgReadPerSecond":0.0,"AvgWritePerSecond":0.00059578}},"100":{"DiskDataSet":{"AvgDiskQueueLength":0.0,"ReadBytesPerSecond":0.0,"WriteBytesPerSecond":0.0,"AvgReadPerSecond":0.0,"AvgWritePerSecond":0.0}},"200":{"DiskDataSet":{"AvgDiskQueueLength":0.0,"ReadBytesPerSecond":0.0,"WriteBytesPerSecond":0.0,"AvgReadPerSecond":0.0,"AvgWritePerSecond":0.0}},"300":{"DiskDataSet":{"AvgDiskQueueLength":0.0,"ReadBytesPerSecond":0.0,"WriteBytesPerSecond":0.0,"AvgReadPerSecond":0.0,"AvgWritePerSecond":0.0}}}]}