{"data":[{"testName":"ProfileList_Create-2","executionTime":322},{"0":{"DiskDataSet":{"AvgDiskQueueLength":0.375823855,"ReadBytesPerSecond":4583114.0,"WriteBytesPerSecond":251231.859,"AvgReadPerSecond":0.0022273038,"AvgWritePerSecond":0.0004390375}},"100":{"DiskDataSet":{"AvgDiskQueueLength":0.479621977,"ReadBytesPerSecond":6425626.0,"WriteBytesPerSecond":0.0,"AvgReadPerSecond":0.00177560688,"AvgWritePerSecond":0.0}},"200":{"DiskDataSet":{"AvgDiskQueueLength":0.358796775,"ReadBytesPerSecond":9073504.0,"WriteBytesPerSecond":0.0,"AvgReadPerSecond":0.000958847639,"AvgWritePerSecond":0.0}}}]}