{"data":[{"testName":"ProfileContentLinkTopDomain-2","executionTime":558},{"0":{"DiskDataSet":{"AvgDiskQueueLength":0.0,"ReadBytesPerSecond":0.0,"WriteBytesPerSecond":0.0,"AvgReadPerSecond":0.0,"AvgWritePerSecond":0.0}},"100":{"DiskDataSet":{"AvgDiskQueueLength":0.0,"ReadBytesPerSecond":0.0,"WriteBytesPerSecond":0.0,"AvgReadPerSecond":0.0,"AvgWritePerSecond":0.0}},"200":{"DiskDataSet":{"AvgDiskQueueLength":0.0,"ReadBytesPerSecond":0.0,"WriteBytesPerSecond":0.0,"AvgReadPerSecond":0.0,"AvgWritePerSecond":0.0}},"300":{"DiskDataSet":{"AvgDiskQueueLength":0.0247469638,"ReadBytesPerSecond":0.0,"WriteBytesPerSecond":298841.781,"AvgReadPerSecond":0.0,"AvgWritePerSecond":0.0027054}},"400":{"DiskDataSet":{"AvgDiskQueueLength":0.00182504323,"ReadBytesPerSecond":0.0,"WriteBytesPerSecond":491696.719,"AvgReadPerSecond":0.0,"AvgWritePerSecond":9.885E-05}}}]}