{"data":[{"testName":"1Setup","executionTime":5599},{"0":{"DiskDataSet":{"AvgDiskQueueLength":0.0,"ReadBytesPerSecond":0.0,"WriteBytesPerSecond":0.0,"AvgReadPerSecond":0.0,"AvgWritePerSecond":0.0}},"100":{"DiskDataSet":{"AvgDiskQueueLength":0.007596101,"ReadBytesPerSecond":1603720.62,"WriteBytesPerSecond":773938.3,"AvgReadPerSecond":0.00114195712,"AvgWritePerSecond":0.000220216}},"200":{"DiskDataSet":{"AvgDiskQueueLength":0.0126108211,"ReadBytesPerSecond":0.0,"WriteBytesPerSecond":644831.2,"AvgReadPerSecond":0.0,"AvgWritePerSecond":0.0001963}},"300":{"DiskDataSet":{"AvgDiskQueueLength":0.0,"ReadBytesPerSecond":0.0,"WriteBytesPerSecond":0.0,"AvgReadPerSecond":0.0,"AvgWritePerSecond":0.0}},"400":{"DiskDataSet":{"AvgDiskQueueLength":0.0,"ReadBytesPerSecond":0.0,"WriteBytesPerSecond":0.0,"AvgReadPerSecond":0.0,"AvgWritePerSecond":0.0}},"500":{"DiskDataSet":{"AvgDiskQueueLength":0.0,"ReadBytesPerSecond":0.0,"WriteBytesPerSecond":0.0,"AvgReadPerSecond":0.0,"AvgWritePerSecond":0.0}},"600":{"DiskDataSet":{"AvgDiskQueueLength":0.09648337,"ReadBytesPerSecond":0.0,"WriteBytesPerSecond":16639953.0,"AvgReadPerSecond":0.0,"AvgWritePerSecond":0.00016081077}},"700":{"DiskDataSet":{"AvgDiskQueueLength":0.00533569744,"ReadBytesPerSecond":0.0,"WriteBytesPerSecond":782111.562,"AvgReadPerSecond":0.0,"AvgWritePerSecond":0.000102416663}},"800":{"DiskDataSet":{"AvgDiskQueueLength":0.0,"ReadBytesPerSecond":0.0,"WriteBytesPerSecond":0.0,"AvgReadPerSecond":0.0,"AvgWritePerSecond":0.0}},"900":{"DiskDataSet":{"AvgDiskQueueLength":0.00477343146,"ReadBytesPerSecond":0.0,"WriteBytesPerSecond":1799613.88,"AvgReadPerSecond":0.0,"AvgWritePerSecond":0.000173933338}},"1000":{"DiskDataSet":{"AvgDiskQueueLength":0.0,"ReadBytesPerSecond":0.0,"WriteBytesPerSecond":0.0,"AvgReadPerSecond":0.0,"AvgWritePerSecond":0.0}},"1100":{"DiskDataSet":{"AvgDiskQueueLength":0.00164757459,"ReadBytesPerSecond":0.0,"WriteBytesPerSecond":599437.9,"AvgReadPerSecond":0.0,"AvgWritePerSecond":0.0001801}},"1200":{"DiskDataSet":{"AvgDiskQueueLength":0.0,"ReadBytesPerSecond":0.0,"WriteBytesPerSecond":0.0,"AvgReadPerSecond":0.0,"AvgWritePerSecond":0.0}},"1300":{"DiskDataSet":{"AvgDiskQueueLength":0.0,"ReadBytesPerSecond":0.0,"WriteBytesPerSecond":0.0,"AvgReadPerSecond":0.0,"AvgWritePerSecond":0.0}},"1400":{"DiskDataSet":{"AvgDiskQueueLength":0.0,"ReadBytesPerSecond":0.0,"WriteBytesPerSecond":0.0,"AvgReadPerSecond":0.0,"AvgWritePerSecond":0.0}},"1500":{"DiskDataSet":{"AvgDiskQueueLength":0.0,"ReadBytesPerSecond":0.0,"WriteBytesPerSecond":0.0,"AvgReadPerSecond":0.0,"AvgWritePerSecond":0.0}},"1600":{"DiskDataSet":{"AvgDiskQueueLength":0.0,"ReadBytesPerSecond":0.0,"WriteBytesPerSecond":0.0,"AvgReadPerSecond":0.0,"AvgWritePerSecond":0.0}},"1700":{"DiskDataSet":{"AvgDiskQueueLength":0.0,"ReadBytesPerSecond":0.0,"WriteBytesPerSecond":0.0,"AvgReadPerSecond":0.0,"AvgWritePerSecond":0.0}},"1800":{"DiskDataSet":{"AvgDiskQueueLength":0.07487873,"ReadBytesPerSecond":0.0,"WriteBytesPerSecond":17822176.0,"AvgReadPerSecond":0.0,"AvgWritePerSecond":0.000458794442}},"1900":{"DiskDataSet":{"AvgDiskQueueLength":1.29192162,"ReadBytesPerSecond":9355.674,"WriteBytesPerSecond":5136959.5,"AvgReadPerSecond":0.0083775,"AvgWritePerSecond":0.00161645969}},"2000":{"DiskDataSet":{"AvgDiskQueueLength":0.0,"ReadBytesPerSecond":0.0,"WriteBytesPerSecond":0.0,"AvgReadPerSecond":0.0,"AvgWritePerSecond":0.0}},"2100":{"DiskDataSet":{"AvgDiskQueueLength":0.0,"ReadBytesPerSecond":0.0,"WriteBytesPerSecond":0.0,"AvgReadPerSecond":0.0,"AvgWritePerSecond":0.0}},"2200":{"DiskDataSet":{"AvgDiskQueueLength":0.0,"ReadBytesPerSecond":0.0,"WriteBytesPerSecond":0.0,"AvgReadPerSecond":0.0,"AvgWritePerSecond":0.0}},"2300":{"DiskDataSet":{"AvgDiskQueueLength":0.0,"ReadBytesPerSecond":0.0,"WriteBytesPerSecond":0.0,"AvgReadPerSecond":0.0,"AvgWritePerSecond":0.0}},"2400":{"DiskDataSet":{"AvgDiskQueueLength":0.0,"ReadBytesPerSecond":0.0,"WriteBytesPerSecond":0.0,"AvgReadPerSecond":0.0,"AvgWritePerSecond":0.0}},"2500":{"DiskDataSet":{"AvgDiskQueueLength":0.0,"ReadBytesPerSecond":0.0,"WriteBytesPerSecond":0.0,"AvgReadPerSecond":0.0,"AvgWritePerSecond":0.0}},"2600":{"DiskDataSet":{"AvgDiskQueueLength":0.0,"ReadBytesPerSecond":0.0,"WriteBytesPerSecond":0.0,"AvgReadPerSecond":0.0,"AvgWritePerSecond":0.0}},"2700":{"DiskDataSet":{"AvgDiskQueueLength":0.0297865067,"ReadBytesPerSecond":0.0,"WriteBytesPerSecond":1800533.5,"AvgReadPerSecond":0.0,"AvgWritePerSecond":0.0010853667}},"2800":{"DiskDataSet":{"AvgDiskQueueLength":0.0,"ReadBytesPerSecond":0.0,"WriteBytesPerSecond":0.0,"AvgReadPerSecond":0.0,"AvgWritePerSecond":0.0}},"2900":{"DiskDataSet":{"AvgDiskQueueLength":0.00107894873,"ReadBytesPerSecond":0.0,"WriteBytesPerSecond":302729.9,"AvgReadPerSecond":0.0,"AvgWritePerSecond":0.0001169}},"3000":{"DiskDataSet":{"AvgDiskQueueLength":0.0,"ReadBytesPerSecond":0.0,"WriteBytesPerSecond":0.0,"AvgReadPerSecond":0.0,"AvgWritePerSecond":0.0}},"3100":{"DiskDataSet":{"AvgDiskQueueLength":0.03265387,"ReadBytesPerSecond":0.0,"WriteBytesPerSecond":14245209.0,"AvgReadPerSecond":0.0,"AvgWritePerSecond":0.00088435}},"3200":{"DiskDataSet":{"AvgDiskQueueLength":0.0,"ReadBytesPerSecond":0.0,"WriteBytesPerSecond":0.0,"AvgReadPerSecond":0.0,"AvgWritePerSecond":0.0}},"3300":{"DiskDataSet":{"AvgDiskQueueLength":0.0,"ReadBytesPerSecond":0.0,"WriteBytesPerSecond":0.0,"AvgReadPerSecond":0.0,"AvgWritePerSecond":0.0}},"3400":{"DiskDataSet":{"AvgDiskQueueLength":0.0,"ReadBytesPerSecond":0.0,"WriteBytesPerSecond":0.0,"AvgReadPerSecond":0.0,"AvgWritePerSecond":0.0}}}]}